asset_sizer/__init__.py
asset_sizer/__main__.py
asset_sizer-0.2.0.dist-info/METADATA
asset_sizer-0.2.0.dist-info/WHEEL
asset_sizer-0.2.0.dist-info/entry_points.txt
asset_sizer-0.2.0.dist-info/RECORD
