Metadata-Version: 2.1
Name: asset-sizer
Version: 0.2.0
Summary: 
License: MIT
Author: Antonio Feregrino
Author-email: antonio.feregrino@gmail.com
Requires-Python: >=3.8,<4.0
Classifier: License :: OSI Approved :: MIT License
Classifier: Programming Language :: Python :: 3
Classifier: Programming Language :: Python :: 3.8
Classifier: Programming Language :: Python :: 3.9
Classifier: Programming Language :: Python :: 3.10
Classifier: Programming Language :: Python :: 3.11
Requires-Dist: imageio (>=2.31.1,<3.0.0)
Requires-Dist: typer (>=0.9.0,<0.10.0)
